django_simple_forms/__init__.py
django_simple_forms/admin.py
django_simple_forms/apps.py
django_simple_forms/forms.py
django_simple_forms/models.py
django_simple_forms/runtests.py
django_simple_forms/urls.py
django_simple_forms/views.py
django_simple_forms/management/__init__.py
django_simple_forms/management/commands/__init__.py
django_simple_forms/management/commands/delete_expired_responses.py
django_simple_forms/management/commands/delete_unused_addresses.py
django_simple_forms/management/commands/forms_import_sites.py
django_simple_forms/migrations/0001_initial.py
django_simple_forms/migrations/__init__.py
django_simple_forms/static/.DS_Store
django_simple_forms/static/admin/.DS_Store
django_simple_forms/static/admin/css/delete_button.css
django_simple_forms/static/admin/css/django_simple_forms.css
django_simple_forms/static/django_simple_forms/.DS_Store
django_simple_forms/static/django_simple_forms/external/.DS_Store
django_simple_forms/static/django_simple_forms/external/css/.DS_Store
django_simple_forms/static/django_simple_forms/external/css/form_style.css
django_simple_forms/static/django_simple_forms/internal/.DS_Store
django_simple_forms/static/django_simple_forms/internal/css/.DS_Store
django_simple_forms/static/django_simple_forms/internal/css/post_html.css
django_simple_forms/templates/.DS_Store
django_simple_forms/templates/django_simple_forms/.DS_Store
django_simple_forms/templates/django_simple_forms/external/.DS_Store
django_simple_forms/templates/django_simple_forms/external/pages/form_page.html
django_simple_forms/templates/django_simple_forms/external/pages/form_submitted.html
django_simple_forms/templates/django_simple_forms/internal/.DS_Store
django_simple_forms/templates/django_simple_forms/internal/internal_base.html
django_simple_forms/templates/django_simple_forms/internal/emails/form_email.html
django_simple_forms/templates/django_simple_forms/internal/emails/form_email.txt
django_simple_forms-0.1.9.dist-info/LICENSE
django_simple_forms-0.1.9.dist-info/METADATA
django_simple_forms-0.1.9.dist-info/WHEEL
django_simple_forms-0.1.9.dist-info/top_level.txt
django_simple_forms-0.1.9.dist-info/zip-safe
django_simple_forms-0.1.9.dist-info/RECORD
